pmark/__init__.py
pmark/benchmark.py
pmark/config_manager.py
pmark/exceptions.py
pmark/logging_config_manager.py
pmark/metadata.json
pmark/metadata.py
pmark/setup.py
pmark/store.py
pmark/string_constants.py
pmark/utils.py
pmark/validations.py
pmark/config/__init__.py
pmark/config/module_config.json
pmark/config/module_config.py
pmark/config/module_logging.yaml
pmark/contrib/__init__.py
pmark/monitors/__init__.py
pmark/monitors/cpu_monitor.py
pmark/monitors/gpu_monitor.py
pmark/monitors/gpustat.py
pmark/monitors/memory_monitor.py
pmark/monitors/monitor.py
pmark/writers/__init__.py
pmark/writers/csv_writer.py
pmark/writers/custom_writer.py
pmark/writers/json_writer.py
pmark/writers/writer.py
pmark-0.0.9.dist-info/METADATA
pmark-0.0.9.dist-info/RECORD
pmark-0.0.9.dist-info/WHEEL
pmark-0.0.9.dist-info/top_level.txt
