Metadata-Version: 2.1
Name: pmark
Version: 0.0.9
Summary: PMark - Python Benchmark, A Simple yet intuitive python process benchmarking utility
Home-page: https://github.com/kingspp/bmark
Author: Prathyush SP
Author-email: kingspprathyush@gmail.com
License: MIT
Keywords: benchmark monitor python
Platform: UNKNOWN
Classifier: Development Status :: 4 - Beta
Classifier: Intended Audience :: Developers
Classifier: Topic :: System :: Benchmark
Classifier: License :: OSI Approved :: MIT License
Classifier: Programming Language :: Python :: 3.5
Classifier: Programming Language :: Python :: 3.6
Provides-Extra: test
Provides-Extra: dev
Requires-Dist: sphinx (==1.5.3)
Requires-Dist: sphinx-rtd-theme
Requires-Dist: gitchangelog
Requires-Dist: sphinx-autodoc-typehints
Requires-Dist: pyyaml
Requires-Dist: nose
Requires-Dist: check-manifest
Requires-Dist: flake8
Requires-Dist: pympler
Requires-Dist: coverage
Requires-Dist: sphinxcontrib-versioning
Requires-Dist: munch
Requires-Dist: psutil
Provides-Extra: dev
Requires-Dist: check-manifest; extra == 'dev'
Provides-Extra: test
Requires-Dist: coverage; extra == 'test'
